{
  "data_dir": "multiwoz/data/usr_data",
  "output_dir": "multiwoz/output/usr",
  "zipped_model_path": "multiwoz/output/usr/bert_multiwoz_usr.zip",
  "log_dir": "multiwoz/log/usr",
  "DEVICE": "cuda:2",
  "seed": 2019,
  "model": {
    "joint": true,
    "finetune": true,
    "pretrained_weights": "/home/data/zhuqi/pre-trained-models/bert-base-uncased",
    "check_step": 1000,
    "max_step": 30000,
    "batch_size": 160,
    "learning_rate": 2e-5,
    "adam_epsilon": 1e-8,
    "warmup_steps": 0,
    "weight_decay": 0.0
  }
}